sequential_circuit/3bit_counter.v
module counter_3bit(
    input clk,
    input reset,
    output reg [2:0] count  
);
always @(posedge clk,posedge reset ) begin
    if(reset)
        count<=3'b000;
    else 
        count=count+1;
end

endmodule



module test_bench;
reg clk;
reg reset;
wire[2:0] count;
counter_3bit uut(clk,reset,count);

always #5 clk=~clk;

initial begin
    $dumpfile("counter.vcd");
    $dumpvars(0, test_bench);
    $monitor("Time: %0t | Reset: %b | Count: %b", $time, reset, count);

    clk=0;
    reset=1;
    #10;
    reset=0;

    #80

    $finish;
end
endmodule

sequential_circuit/counter.vcd
$date
	Fri May 16 20:55:09 2025
$end
$version
	Icarus Verilog
$end
$timescale
	1s
$end
$scope module test_bench $end
$var wire 3 ! count [2:0] $end
$var reg 1 " clk $end
$var reg 1 # reset $end
$scope module uut $end
$var wire 1 " clk $end
$var wire 1 # reset $end
$var reg 3 $ count [2:0] $end
$upscope $end
$upscope $end
$enddefinitions $end
$comment Show the parameter values. $end
$dumpall
$end
#0
$dumpvars
b0 $
1#
0"
b0 !
$end
#5
1"
#10
0"
0#
#15
b1 !
b1 $
1"
#20
0"
#25
b10 !
b10 $
1"
#30
0"
#35
b11 !
b11 $
1"
#40
0"
#45
b100 !
b100 $
1"
#50
0"
#55
b101 !
b101 $
1"
#60
0"
#65
b110 !
b110 $
1"
#70
0"
#75
b111 !
b111 $
1"
#80
0"
#85
b0 !
b0 $
1"
