LAB/Task02/task02.v
//CO224 - verilog Lab: Task 02
// E number - E/21/087



// -----------------------------------
//            Counter
// -----------------------------------

module four_bit_counter(clk,Enable,Reset,count);

input clk;
input Enable;
input Reset;
output reg [3:0]count;

//Always bloock triggered on rising edge
always @(posedge clk) begin
    if(Reset)
        count<=4'b0000;   // Reset the count
    else if(Enable)
        count<=count+1;   //increment the count
end
endmodule



// -----------------------------------
//            Test bench 
// -----------------------------------


module test_bench;

reg clk,reset,enable;
wire [3:0] count;

four_bit_counter uut(clk,enable,reset,count);


//clock generation
initial begin
    clk=0;
    forever #5 clk=~clk;
end

initial begin
    // Reset the counter
    reset=1;
end

initial begin
    $monitor("Time = %0t | reset = %b | enable = %b => count = %b (%0d)", $time,reset, enable, count, count);
    $dumpfile ("task2.vcd"); 
    $dumpvars(0,test_bench);

    #10
    reset=0;         // Deassert reset
    enable=1;        // Enable counting

    #50
    enable=0;        // Pause counting

    #20
    enable=1;        // Resume counting

    #30
    reset=1;         // Reset counting

    #10;
    reset=0;         // Deassert reset

    #20;
    $finish;
end

    
endmodule

LAB/Task02/task2.vcd
$date
	Sun May 18 19:15:00 2025
$end
$version
	Icarus Verilog
$end
$timescale
	1s
$end
$scope module test_bench $end
$var wire 4 ! count [3:0] $end
$var reg 1 " clk $end
$var reg 1 # enable $end
$var reg 1 $ reset $end
$scope module uut $end
$var wire 1 # Enable $end
$var wire 1 $ Reset $end
$var wire 1 " clk $end
$var reg 4 % count [3:0] $end
$upscope $end
$upscope $end
$enddefinitions $end
$comment Show the parameter values. $end
$dumpall
$end
#0
$dumpvars
bx %
1$
x#
0"
bx !
$end
#5
b0 !
b0 %
1"
#10
0"
1#
0$
#15
b1 !
b1 %
1"
#20
0"
#25
b10 !
b10 %
1"
#30
0"
#35
b11 !
b11 %
1"
#40
0"
#45
b100 !
b100 %
1"
#50
0"
#55
b101 !
b101 %
1"
#60
0"
0#
#65
1"
#70
0"
#75
1"
#80
0"
1#
#85
b110 !
b110 %
1"
#90
0"
#95
b111 !
b111 %
1"
#100
0"
#105
b1000 !
b1000 %
1"
#110
0"
1$
#115
b0 !
b0 %
1"
#120
0"
0$
#125
b1 !
b1 %
1"
#130
0"
#135
b10 !
b10 %
1"
