Exercise/Ex1.v
module testbench;

    reg clk, reset;
    wire [1:0] q;

    // Instantiate the counter
    two_bit_counter uut(clk, reset, q);

    // Clock generation
    always #5 clk = ~clk;  // 10 time unit period

    initial begin
        $dumpfile("counter.vcd");
        $dumpvars(0, testbench);
        $display("Time=%0t | Counter = %b", $time, q);

        clk = 0;
        reset = 1;       // Apply reset
        #10;
        reset = 0;       // Release reset

        // Observe for several clock cycles
        repeat (10) begin
            #10;
            $display("Time=%0t | Counter = %b", $time, q);
        end

        $finish;
    end

endmodule



module two_bit_counter (
    input clk,
    input reset,
    output [1:0] q
);
    wire q0, q1;
    wire q0_bar, q1_bar;

    d_ff ff0(clk, reset, q0_bar, q0, q0_bar);         // Toggled every clock
    d_ff ff1(q0, reset, q1_bar, q1, q1_bar);           // Toggled on q0 rising

    assign q = {q1, q0};

endmodule



module d_ff (
    input clk,
    input reset,
    input D,
    output reg Q,
    output Q_bar
);
    assign Q_bar = ~Q;

    always @(posedge clk or posedge reset) begin
        if (reset)
            Q <= 1'b0;
        else
            Q <= D;
    end
endmodule

Exercise/counter.vcd
$date
	Sun May 18 16:25:16 2025
$end
$version
	Icarus Verilog
$end
$timescale
	1s
$end
$scope module testbench $end
$var wire 2 ! q [1:0] $end
$var reg 1 " clk $end
$var reg 1 # reset $end
$scope module uut $end
$var wire 1 " clk $end
$var wire 1 # reset $end
$var wire 1 $ q1_bar $end
$var wire 1 % q1 $end
$var wire 1 & q0_bar $end
$var wire 1 ' q0 $end
$var wire 2 ( q [1:0] $end
$scope module ff0 $end
$var wire 1 & D $end
$var wire 1 & Q_bar $end
$var wire 1 " clk $end
$var wire 1 # reset $end
$var reg 1 ' Q $end
$upscope $end
$scope module ff1 $end
$var wire 1 $ D $end
$var wire 1 $ Q_bar $end
$var wire 1 ' clk $end
$var wire 1 # reset $end
$var reg 1 % Q $end
$upscope $end
$upscope $end
$upscope $end
$enddefinitions $end
$comment Show the parameter values. $end
$dumpall
$end
#0
$dumpvars
b0 (
0'
1&
0%
1$
1#
0"
b0 !
$end
#5
1"
#10
0"
0#
#15
0$
1%
0&
b11 !
b11 (
1'
1"
#20
0"
#25
1&
b10 !
b10 (
0'
1"
#30
0"
#35
1$
0%
0&
b1 !
b1 (
1'
1"
#40
0"
#45
1&
b0 !
b0 (
0'
1"
#50
0"
#55
0$
1%
0&
b11 !
b11 (
1'
1"
#60
0"
#65
1&
b10 !
b10 (
0'
1"
#70
0"
#75
1$
0%
0&
b1 !
b1 (
1'
1"
#80
0"
#85
1&
b0 !
b0 (
0'
1"
#90
0"
#95
0$
1%
0&
b11 !
b11 (
1'
1"
#100
0"
#105
1&
b10 !
b10 (
0'
1"
