Exercise/Ex2_3.v
//  Using SR Latch to Build a D Flip-Flop
module d_filp_flop(
    input clk,
    input D,
    output reg q,
    output q_bar
);

reg s,r;

assign q_bar=~q;

always@(posedge clk) begin
    s=clk &  D;
    r=clk & ~D;

    case({s,r})
        2'b00 : q<=q;
        2'b01 : q<=0;
        2'b10 : q<=1;
        2'b11 : q<=1'bx;
    endcase
end

endmodule

module test_bench;
reg clk;
reg d;
wire q,q_bar;

d_filp_flop uut(clk,d,q,q_bar);
//Clock generate
always #5 clk=~clk;

initial begin
    $dumpfile("d_ff.vcd");
    $dumpvars(0,test_bench);
    clk=0;
    d = 1; #10;
    d = 0; #10;
    d = 1; #10;
    d = 1; #10;
    d = 0; #10;
    d = 1; #10;

    #20;
    $finish;
end
endmodule

Exercise/d_ff.vcd
$date
	Sun May 18 15:53:34 2025
$end
$version
	Icarus Verilog
$end
$timescale
	1s
$end
$scope module test_bench $end
$var wire 1 ! q_bar $end
$var wire 1 " q $end
$var reg 1 # clk $end
$var reg 1 $ d $end
$scope module uut $end
$var wire 1 $ D $end
$var wire 1 # clk $end
$var wire 1 ! q_bar $end
$var reg 1 " q $end
$var reg 1 % r $end
$var reg 1 & s $end
$upscope $end
$upscope $end
$enddefinitions $end
$comment Show the parameter values. $end
$dumpall
$end
#0
$dumpvars
x&
x%
1$
0#
x"
x!
$end
#5
0!
1"
0%
1&
1#
#10
0#
0$
#15
1!
0"
1%
0&
1#
#20
0#
1$
#25
0!
1"
0%
1&
1#
#30
0#
#35
1#
#40
0#
0$
#45
1!
0"
1%
0&
1#
#50
0#
1$
#55
0!
1"
0%
1&
1#
