Exercise/Ex2_1.v
// D Flip-Flop (Behavioral Modeling)
// Stores the input D on the rising edge of the clock

module D_flip_flop(
    input clk,
    input REST,
    input D,
    output reg Q
) ;

always @(posedge clk)
begin
    if(REST)
        Q<=1'b0;
    else
        Q<=D;
end

endmodule

module test_bench;
    reg clk,rest,d;
    wire Q;
    D_flip_flop uut(clk,rest,d,q);
    
    //Clock generate
    always #5 clk=~clk;

    initial begin
        $dumpfile("d_flip_flop.vcd"); 
        $dumpvars(0, test_bench);

        clk=0;
        rest=1;
        d=0;

        #10
        rest=0;

        d=1;
        #10;
        d=0;
        #10;
        d=1;
        #10;

        #20
        $finish;
        
    end
endmodule

Exercise/d_flip_flop.vcd
$date
	Fri May 16 23:04:35 2025
$end
$version
	Icarus Verilog
$end
$timescale
	1s
$end
$scope module test_bench $end
$var wire 1 ! q $end
$var reg 1 " clk $end
$var reg 1 # d $end
$var reg 1 $ rest $end
$scope module uut $end
$var wire 1 # D $end
$var wire 1 $ REST $end
$var wire 1 " clk $end
$var reg 1 ! Q $end
$upscope $end
$upscope $end
$enddefinitions $end
$comment Show the parameter values. $end
$dumpall
$end
#0
$dumpvars
1$
0#
0"
x!
$end
#5
0!
1"
#10
0"
1#
0$
#15
1!
1"
#20
0"
0#
#25
0!
1"
#30
0"
1#
#35
1!
1"
