Exercise/Ex2_2.v
module SR_filp_flop(
    input clk,
    input reset,
    input S,R,
    output reg Q
);

always @(posedge clk) begin
    if(reset)
        Q<=0;
    else begin 
        case({S,R})
            2'b00: Q <= Q;
            2'b01: Q <= 0;
            2'b10: Q <= 1;
            2'b11: Q <= 1'bx;

        endcase
    end 
end

endmodule

module test_bench;

    reg clk;
    reg rst;
    reg s, r;
    wire q;

    // Instantiate the SR flip-flop
    SR_filp_flop uut (clk,rst,s,r,q);

    // Clock generation
    always #5 clk = ~clk;

    initial begin
        $dumpfile("sr_flip_flop.vcd");
        $dumpvars(0, test_bench);

        // Initialize signals
        clk = 0; rst = 1; s = 0; r = 0;
        #10 rst = 0;

        // Test Set
        s = 1; r = 0; #10;

        // Test Reset
        s = 0; r = 1; #10;

        // Test No Change
        s = 0; r = 0; #10;

        // Test Invalid
        s = 1; r = 1; #10;

        // Finish
        #10;
        $finish;
    end

endmodule

Exercise/sr_flip_flop.vcd
$date
	Fri May 16 23:21:24 2025
$end
$version
	Icarus Verilog
$end
$timescale
	1s
$end
$scope module test_bench $end
$var wire 1 ! q $end
$var reg 1 " clk $end
$var reg 1 # r $end
$var reg 1 $ rst $end
$var reg 1 % s $end
$scope module uut $end
$var wire 1 # R $end
$var wire 1 % S $end
$var wire 1 " clk $end
$var wire 1 $ reset $end
$var reg 1 ! Q $end
$upscope $end
$upscope $end
$enddefinitions $end
$comment Show the parameter values. $end
$dumpall
$end
#0
$dumpvars
0%
1$
0#
0"
x!
$end
#5
0!
1"
#10
0"
1%
0$
#15
1!
1"
#20
0"
1#
0%
#25
0!
1"
#30
0"
0#
#35
1"
#40
0"
1#
1%
#45
x!
1"
