Full_Adder/full_adder.v
module test_bench;

reg A_test,B_test,Ci_test;
wire S_test,Co_test;

full_adder uut(A_test,B_test,Ci_test,S_test,Co_test);

initial begin
    $monitor("A: %b, B: %b, Cin: %b, Sum: %b, Cout: %b",A_test,B_test,Ci_test,S_test,Co_test);
    $dumpfile("full_adder.vcd");
    $dumpvars(0,test_bench);
    
    // Apply all combinations
    A_test = 0; B_test = 0; Ci_test = 0;
    #10;

    A_test = 0; B_test = 0; Ci_test = 1; 
    #10;

    A_test = 0; B_test = 1; Ci_test = 0; 
    #10;

    A_test = 0; B_test = 1; Ci_test = 1; 
    #10;

    A_test = 1; B_test = 0; Ci_test= 0; 
    #10;

    A_test = 1; B_test = 0; Ci_test = 1; 
    #10;

    A_test = 1; B_test = 1; Ci_test = 0; 
    #10;

    A_test = 1; B_test = 1; Ci_test = 1; 
    #10;
    $finish;

end


endmodule



module full_adder(A,B,Ci,S,Co);

input A,B,Ci;
output  S,Co;
//using behavioral modeling
// assign S=A^B^Ci;
// assign Co=(A & B) | (A & Ci) | (B & Ci);

//using behavioral modeling
// input A,B,Ci;
// output reg S,Co;
// always @(A,B,Ci) begin
//     {Co,S}=A+B+Ci;
// end


//using gate level modeling
wire w1,w2,w3;
xor (w1,A,B);
xor (S,w1,Ci);

and (w2,Ci,w1);
and (w3,A,B);
or (Co,w2,w3);



endmodule

Full_Adder/full_adder.vcd
$date
	Fri May 16 19:05:08 2025
$end
$version
	Icarus Verilog
$end
$timescale
	1s
$end
$scope module test_bench $end
$var wire 1 ! S_test $end
$var wire 1 " Co_test $end
$var reg 1 # A_test $end
$var reg 1 $ B_test $end
$var reg 1 % Ci_test $end
$scope module uut $end
$var wire 1 # A $end
$var wire 1 $ B $end
$var wire 1 % Ci $end
$var wire 1 " Co $end
$var wire 1 ! S $end
$var wire 1 & w1 $end
$var wire 1 ' w2 $end
$var wire 1 ( w3 $end
$upscope $end
$upscope $end
$enddefinitions $end
$comment Show the parameter values. $end
$dumpall
$end
#0
$dumpvars
0(
0'
0&
0%
0$
0#
0"
0!
$end
#10
1!
1%
#20
1&
0%
1$
#30
1"
0!
1'
1%
#40
0"
1!
0'
0%
0$
1#
#50
1"
0!
1'
1%
#60
0'
0&
1(
0%
1$
#70
1!
1%
